{
  "objectInfo" : {
    "id" : "1g9RIHUrJxBlCNOFO3UwAr",
    "name" : "VCS_PROJ_AUTO_CUSTOM",
    "type" : "Project",
    "metadata" : {
      "modelVersion" : {
        "major" : 0,
        "minor" : 0
      },
      "repoInfo" : null,
      "contextAttributes" : [ ],
      "additionalInfo" : {
        "description" : "",
        "contentType" : "Binary",
        "documentState" : "COMPLETE"
      }
    }
  },
  "dataFileExtension" : "json",
  "updateTime" : "2024-08-01T04:49:26.187Z",
  "objectRefs" : [ ]
}